datascience_quickstarter-1.1.0.data/data/LICENSE
datascience_quickstarter-1.1.0.data/data/README.md
datascience_quickstarter-1.1.0.data/data/VERSION
quickstarter/__init__.py
quickstarter/create_demo.py
quickstarter/create_project.py
quickstarter/utils.py
quickstarter/templates/demo/Dockerfile
quickstarter/templates/demo/Makefile
quickstarter/templates/demo/README.md
quickstarter/templates/demo/VERSION
quickstarter/templates/demo/demo.py
quickstarter/templates/demo/requirements_demo.txt
quickstarter/templates/project/.gitignore
quickstarter/templates/project/Dockerfile
quickstarter/templates/project/Makefile
quickstarter/templates/project/README.md
quickstarter/templates/project/VERSION
quickstarter/templates/project/example_module.py
quickstarter/templates/project/example_request.json
quickstarter/templates/project/example_requests.py
quickstarter/templates/project/requirements.txt
quickstarter/templates/project/schema.proto
quickstarter/templates/project/serving.py
quickstarter/templates/project/setup.py
quickstarter/templates/project/test_serving.py
datascience_quickstarter-1.1.0.dist-info/LICENSE
datascience_quickstarter-1.1.0.dist-info/METADATA
datascience_quickstarter-1.1.0.dist-info/WHEEL
datascience_quickstarter-1.1.0.dist-info/entry_points.txt
datascience_quickstarter-1.1.0.dist-info/top_level.txt
datascience_quickstarter-1.1.0.dist-info/RECORD
