Metadata-Version: 2.1
Name: datascience-quickstarter
Version: 1.1.0
Summary: A tool for quick-starting new datascience projects, built by AYLIEN Labs.
License-File: LICENSE
